[
  {
    "TRANSNR": "27662",
    "TRANSTYPE": "Salg",
    "KONTO": "AUTH-0215",
    "AFTALE": "AFT-2024-017",
    "ARTNR": "978-87-3823-692-2",
    "KANAL": "Online",
    "PRISGRUPPE": "Special",
    "VILKAR": "D",
    "BILAGSNR": "66287",
    "BILAGSDATO": "27-12-2023",
    "ANTAL": "1036",
    "STKPRIS": "73.01",
    "STKAFREGNSATS": "0.1235",
    "BELOEB": "9341.34",
    "VALUTA": "DKK",
    "SKAT": "0.00",
    "AFREGNBATCH": "6643"
  },
  {
    "TRANSNR": "27663",
    "TRANSTYPE": "Frieksp",
    "KONTO": "AUTH-0215",
    "AFTALE": "AFT-2024-017",
    "ARTNR": "978-87-3736-710-8",
    "KANAL": "Boghandel",
    "PRISGRUPPE": "Klassiker",
    "VILKAR": "D",
    "BILAGSNR": "95568",
    "BILAGSDATO": "07-01-2024",
    "ANTAL": "1700",
    "STKPRIS": "571.66",
    "STKAFREGNSATS": "0.2269",
    "BELOEB": "220506.41",
    "VALUTA": "DKK",
    "SKAT": "0.00",
    "AFREGNBATCH": "6643"
  },
  {
    "TRANSNR": "27664",
    "TRANSTYPE": "Korrektion",
    "KONTO": "AUTH-0215",
    "AFTALE": "AFT-2024-017",
    "ARTNR": "978-87-1865-537-8",
    "KANAL": "Online",
    "PRISGRUPPE": "Digital",
    "VILKAR": "A",
    "BILAGSNR": "73346",
    "BILAGSDATO": "06-02-2024",
    "ANTAL": "1313",
    "STKPRIS": "269.47",
    "STKAFREGNSATS": "0.2023",
    "BELOEB": "71576.59",
    "VALUTA": "DKK",
    "SKAT": "0.00",
    "AFREGNBATCH": "6643"
  },
  {
    "TRANSNR": "27665",
    "TRANSTYPE": "Frieksp",
    "KONTO": "AUTH-0215",
    "AFTALE": "AFT-2024-017",
    "ARTNR": "978-87-1806-906-9",
    "KANAL": "Eksport",
    "PRISGRUPPE": "Klassiker",
    "VILKAR": "B",
    "BILAGSNR": "60670",
    "BILAGSDATO": "09-01-2024",
    "ANTAL": "348",
    "STKPRIS": "235.57",
    "STKAFREGNSATS": "0.1869",
    "BELOEB": "15321.76",
    "VALUTA": "DKK",
    "SKAT": "0.00",
    "AFREGNBATCH": "6643"
  },
  {
    "TRANSNR": "27666",
    "TRANSTYPE": "Salg",
    "KONTO": "AUTH-0215",
    "AFTALE": "AFT-2024-017",
    "ARTNR": "",
    "KANAL": "Subskription",
    "PRISGRUPPE": "Indbundet",
    "VILKAR": "B",
    "BILAGSNR": "68917",
    "BILAGSDATO": "18-12-2023",
    "ANTAL": "1641",
    "STKPRIS": "495.82",
    "STKAFREGNSATS": "0.1304",
    "BELOEB": "106098.74",
    "VALUTA": "DKK",
    "SKAT": "0.00",
    "AFREGNBATCH": "6643"
  },
  {
    "TRANSNR": "27667",
    "TRANSTYPE": "Salg",
    "KONTO": "AUTH-0215",
    "AFTALE": "AFT-2024-017",
    "ARTNR": "978-87-4019-293-3",
    "KANAL": "Online",
    "PRISGRUPPE": "Pocket",
    "VILKAR": "A",
    "BILAGSNR": "63043",
    "BILAGSDATO": "23-12-2023",
    "ANTAL": "154",
    "STKPRIS": "206.81",
    "STKAFREGNSATS": "0.0614",
    "BELOEB": "1955.51",
    "VALUTA": "DKK",
    "SKAT": "0.00",
    "AFREGNBATCH": "6643"
  },
  {
    "TRANSNR": "27668",
    "TRANSTYPE": "Salg",
    "KONTO": "AUTH-0215",
    "AFTALE": "AFT-2024-017",
    "ARTNR": "978-87-2688-250-6",
    "KANAL": "Boghandel",
    "PRISGRUPPE": "Pocket",
    "VILKAR": "B",
    "BILAGSNR": "54285",
    "BILAGSDATO": "25-12-2023",
    "ANTAL": "257",
    "STKPRIS": "361.77",
    "STKAFREGNSATS": "0.1205",
    "BELOEB": "11203.47",
    "VALUTA": "DKK",
    "SKAT": "0.00",
    "AFREGNBATCH": "6643"
  },
  {
    "TRANSNR": "27669",
    "TRANSTYPE": "Retur",
    "KONTO": "AUTH-0215",
    "AFTALE": "AFT-2024-017",
    "ARTNR": "978-87-4433-708-8",
    "KANAL": "Subskription",
    "PRISGRUPPE": "Special",
    "VILKAR": "B",
    "BILAGSNR": "72598",
    "BILAGSDATO": "21-12-2023",
    "ANTAL": "-714",
    "STKPRIS": "82.97",
    "STKAFREGNSATS": "",
    "BELOEB": "-7677.58",
    "VALUTA": "DKK",
    "SKAT": "0.00",
    "AFREGNBATCH": "6643"
  },
  {
    "TRANSNR": "27670",
    "TRANSTYPE": "Bonus",
    "KONTO": "AUTH-0215",
    "AFTALE": "AFT-2024-017",
    "ARTNR": "978-87-9949-446-0",
    "KANAL": "Eksport",
    "PRISGRUPPE": "Standard",
    "VILKAR": "C",
    "BILAGSNR": "91833",
    "BILAGSDATO": "27-12-2023",
    "ANTAL": "578",
    "STKPRIS": "394.13",
    "STKAFREGNSATS": "0.2224",
    "BELOEB": "50664.31",
    "VALUTA": "DKK",
    "SKAT": "0.00",
    "AFREGNBATCH": "6643"
  },
  {
    "TRANSNR": "27671",
    "TRANSTYPE": "Frieksp",
    "KONTO": "AUTH-0215",
    "AFTALE": "AFT-2024-017",
    "ARTNR": "978-87-2919-199-5",
    "KANAL": "Subskription",
    "PRISGRUPPE": "Special",
    "VILKAR": "D",
    "BILAGSNR": "57249",
    "BILAGSDATO": "23-12-2023",
    "ANTAL": "1769",
    "STKPRIS": "327.07",
    "STKAFREGNSATS": "0.1433",
    "BELOEB": "82911.49",
    "VALUTA": "DKK",
    "SKAT": "0.00",
    "AFREGNBATCH": "6643"
  },
  {
    "TRANSNR": "27672",
    "TRANSTYPE": "Salg",
    "KONTO": "AUTH-0215",
    "AFTALE": "AFT-2024-017",
    "ARTNR": "978-87-6988-631-8",
    "KANAL": "Boghandel",
    "PRISGRUPPE": "Indbundet",
    "VILKAR": "D",
    "BILAGSNR": "75414",
    "BILAGSDATO": "30-01-2024",
    "ANTAL": "641",
    "STKPRIS": "421.70",
    "STKAFREGNSATS": "0.2098",
    "BELOEB": "56710.98",
    "VALUTA": "DKK",
    "SKAT": "0.00",
    "AFREGNBATCH": "6643"
  },
  {
    "TRANSNR": "27673",
    "TRANSTYPE": "Salg",
    "KONTO": "AUTH-0215",
    "AFTALE": "AFT-2024-017",
    "ARTNR": "978-87-7157-491-3",
    "KANAL": "Boghandel",
    "PRISGRUPPE": "Digital",
    "VILKAR": "D",
    "BILAGSNR": "63641",
    "BILAGSDATO": "28-12-2023",
    "ANTAL": "810",
    "STKPRIS": "585.76",
    "STKAFREGNSATS": "0.1193",
    "BELOEB": "56603.75",
    "VALUTA": "DKK",
    "SKAT": "0.00",
    "AFREGNBATCH": "6643"
  },
  {
    "TRANSNR": "27674",
    "TRANSTYPE": "Salg",
    "KONTO": "AUTH-0215",
    "AFTALE": "AFT-2024-017",
    "ARTNR": "978-87-5973-396-7",
    "KANAL": "E-bog",
    "PRISGRUPPE": "Indbundet",
    "VILKAR": "D",
    "BILAGSNR": "93804",
    "BILAGSDATO": "22-12-2023",
    "ANTAL": "1879",
    "STKPRIS": "533.44",
    "STKAFREGNSATS": "0.0823",
    "BELOEB": "82215.50",
    "VALUTA": "DKK",
    "SKAT": "0.00",
    "AFREGNBATCH": "6643"
  },
  {
    "TRANSNR": "27675",
    "TRANSTYPE": "Salg",
    "KONTO": "AUTH-0215",
    "AFTALE": "AFT-2024-017",
    "ARTNR": "978-87-1357-358-5",
    "KANAL": "Online",
    "PRISGRUPPE": "Lydbog",
    "VILKAR": "D",
    "BILAGSNR": "62021",
    "BILAGSDATO": "30-01-2024",
    "ANTAL": "1306",
    "STKPRIS": "502.22",
    "STKAFREGNSATS": "0.124",
    "BELOEB": "81331.52",
    "VALUTA": "DKK",
    "SKAT": "0.00",
    "AFREGNBATCH": "6643"
  },
  {
    "TRANSNR": "27676",
    "TRANSTYPE": "Salg",
    "KONTO": "AUTH-0215",
    "AFTALE": "AFT-2024-017",
    "ARTNR": "978-87-5191-090-8",
    "KANAL": "E-bog",
    "PRISGRUPPE": "Indbundet",
    "VILKAR": "C",
    "BILAGSNR": "63483",
    "BILAGSDATO": "19-12-2023",
    "ANTAL": "713",
    "STKPRIS": "68.05",
    "STKAFREGNSATS": "0.1018",
    "BELOEB": "4939.30",
    "VALUTA": "DKK",
    "SKAT": "0.00",
    "AFREGNBATCH": "6643"
  },
  {
    "TRANSNR": "27677",
    "TRANSTYPE": "Royalty",
    "KONTO": "AUTH-0215",
    "AFTALE": "AFT-2024-017",
    "ARTNR": "978-87-6467-202-2",
    "KANAL": "Subskription",
    "PRISGRUPPE": "Pocket",
    "VILKAR": "D",
    "BILAGSNR": "78188",
    "BILAGSDATO": "14-01-2024",
    "ANTAL": "1456",
    "STKPRIS": "375.02",
    "STKAFREGNSATS": "0.1081",
    "BELOEB": "59025.75",
    "VALUTA": "DKK",
    "SKAT": "0.00",
    "AFREGNBATCH": "6643"
  },
  {
    "TRANSNR": "27678",
    "TRANSTYPE": "Salg",
    "KONTO": "AUTH-0215",
    "AFTALE": "AFT-2024-017",
    "ARTNR": "978-87-3515-290-4",
    "KANAL": "Online",
    "PRISGRUPPE": "Pocket",
    "VILKAR": "C",
    "BILAGSNR": "93494",
    "BILAGSDATO": "26-01-2024",
    "ANTAL": "401",
    "STKPRIS": "501.52",
    "STKAFREGNSATS": "0.2253",
    "BELOEB": "45581.04",
    "VALUTA": "DKK",
    "SKAT": "0.00",
    "AFREGNBATCH": "6643"
  },
  {
    "TRANSNR": "27679",
    "TRANSTYPE": "Royalty",
    "KONTO": "AUTH-0215",
    "AFTALE": "AFT-2024-017",
    "ARTNR": "978-87-4604-953-8",
    "KANAL": "Online",
    "PRISGRUPPE": "Special",
    "VILKAR": "A",
    "BILAGSNR": "72784",
    "BILAGSDATO": "10-01-2024",
    "ANTAL": "1938",
    "STKPRIS": "442.73",
    "STKAFREGNSATS": "0.1802",
    "BELOEB": "154613.54",
    "VALUTA": "DKK",
    "SKAT": "0.00",
    "AFREGNBATCH": "6643"
  },
  {
    "TRANSNR": "27680",
    "TRANSTYPE": "Retur",
    "KONTO": "AUTH-0215",
    "AFTALE": "AFT-2024-017",
    "ARTNR": "978-87-5035-995-1",
    "KANAL": "E-bog",
    "PRISGRUPPE": "Klassiker",
    "VILKAR": "D",
    "BILAGSNR": "74602",
    "BILAGSDATO": "18-01-2024",
    "ANTAL": "-910",
    "STKPRIS": "136.78",
    "STKAFREGNSATS": "0.0648",
    "BELOEB": "-8065.64",
    "VALUTA": "DKK",
    "SKAT": "0.00",
    "AFREGNBATCH": "6643"
  },
  {
    "TRANSNR": "27681",
    "TRANSTYPE": "Salg",
    "KONTO": "AUTH-0215",
    "AFTALE": "AFT-2024-017",
    "ARTNR": "978-87-0700-000-4",
    "KANAL": "Online",
    "PRISGRUPPE": "Indbundet",
    "VILKAR": "D",
    "BILAGSNR": "95031",
    "BILAGSDATO": "23-01-2024",
    "ANTAL": "1566",
    "STKPRIS": "482.33",
    "STKAFREGNSATS": "0.2137",
    "BELOEB": "161413.76",
    "VALUTA": "DKK",
    "SKAT": "0.00",
    "AFREGNBATCH": "6643"
  },
  {
    "TRANSNR": "27682",
    "TRANSTYPE": "Salg",
    "KONTO": "AUTH-0215",
    "AFTALE": "AFT-2024-017",
    "ARTNR": "978-87-3556-233-8",
    "KANAL": "Eksport",
    "PRISGRUPPE": "Klassiker",
    "VILKAR": "A",
    "BILAGSNR": "92586",
    "BILAGSDATO": "08-01-2024",
    "ANTAL": "160",
    "STKPRIS": "326.97",
    "STKAFREGNSATS": "0.1404",
    "BELOEB": "7345.05",
    "VALUTA": "DKK",
    "SKAT": "0.00",
    "AFREGNBATCH": "6643"
  },
  {
    "TRANSNR": "27683",
    "TRANSTYPE": "Salg",
    "KONTO": "AUTH-0215",
    "AFTALE": "AFT-2024-017",
    "ARTNR": "978-87-7272-578-9",
    "KANAL": "Boghandel",
    "PRISGRUPPE": "Standard",
    "VILKAR": "A",
    "BILAGSNR": "66871",
    "BILAGSDATO": "28-01-2024",
    "ANTAL": "1153",
    "STKPRIS": "436.94",
    "STKAFREGNSATS": "0.206",
    "BELOEB": "103781.11",
    "VALUTA": "DKK",
    "SKAT": "0.00",
    "AFREGNBATCH": "6643"
  },
  {
    "TRANSNR": "27684",
    "TRANSTYPE": "Forskud",
    "KONTO": "AUTH-0215",
    "AFTALE": "AFT-2024-017",
    "ARTNR": "978-87-4244-661-4",
    "KANAL": "Bibliotek",
    "PRISGRUPPE": "Standard",
    "VILKAR": "C",
    "BILAGSNR": "55038",
    "BILAGSDATO": "16-01-2024",
    "ANTAL": "1783",
    "STKPRIS": "558.41",
    "STKAFREGNSATS": "0.172",
    "BELOEB": "171250.95",
    "VALUTA": "DKK",
    "SKAT": "0.00",
    "AFREGNBATCH": "6643"
  },
  {
    "TRANSNR": "27685",
    "TRANSTYPE": "Korrektion",
    "KONTO": "AUTH-0215",
    "AFTALE": "AFT-2024-017",
    "ARTNR": "978-87-7025-267-6",
    "KANAL": "Boghandel",
    "PRISGRUPPE": "Standard",
    "VILKAR": "A",
    "BILAGSNR": "60852",
    "BILAGSDATO": "18-12-2023",
    "ANTAL": "529",
    "STKPRIS": "289.81",
    "STKAFREGNSATS": "0.2371",
    "BELOEB": "36349.68",
    "VALUTA": "DKK",
    "SKAT": "0.00",
    "AFREGNBATCH": "6643"
  },
  {
    "TRANSNR": "27686",
    "TRANSTYPE": "Retur",
    "KONTO": "AUTH-0215",
    "AFTALE": "AFT-2024-017",
    "ARTNR": "978-87-0605-492-3",
    "KANAL": "Online",
    "PRISGRUPPE": "Pocket",
    "VILKAR": "A",
    "BILAGSNR": "78801",
    "BILAGSDATO": "10-02-2024",
    "ANTAL": "-724",
    "STKPRIS": "326.19",
    "STKAFREGNSATS": "0.1246",
    "BELOEB": "-29425.73",
    "VALUTA": "DKK",
    "SKAT": "0.00",
    "AFREGNBATCH": "6643"
  },
  {
    "TRANSNR": "27687",
    "TRANSTYPE": "Salg",
    "KONTO": "AUTH-0215",
    "AFTALE": "AFT-2024-017",
    "ARTNR": "978-87-9466-680-0",
    "KANAL": "Eksport",
    "PRISGRUPPE": "Digital",
    "VILKAR": "B",
    "BILAGSNR": "87410",
    "BILAGSDATO": "02-01-2024",
    "ANTAL": "1592",
    "STKPRIS": "68.97",
    "STKAFREGNSATS": "N/A",
    "BELOEB": "26187.36",
    "VALUTA": "DKK",
    "SKAT": "0.00",
    "AFREGNBATCH": "6643"
  },
  {
    "TRANSNR": "27688",
    "TRANSTYPE": "Salg",
    "KONTO": "AUTH-0215",
    "AFTALE": "AFT-2024-017",
    "ARTNR": "978-87-2449-342-1",
    "KANAL": "E-bog",
    "PRISGRUPPE": "Klassiker",
    "VILKAR": "B",
    "BILAGSNR": "55413",
    "BILAGSDATO": "14-01-2024",
    "ANTAL": "1559",
    "STKPRIS": "331.95",
    "STKAFREGNSATS": "0.1369",
    "BELOEB": "70847.13",
    "VALUTA": "DKK",
    "SKAT": "0.00",
    "AFREGNBATCH": "6643"
  },
  {
    "TRANSNR": "27689",
    "TRANSTYPE": "Salg",
    "KONTO": "AUTH-0215",
    "AFTALE": "AFT-2024-017",
    "ARTNR": "978-87-5230-066-1",
    "KANAL": "Online",
    "PRISGRUPPE": "Indbundet",
    "VILKAR": "A",
    "BILAGSNR": "96984",
    "BILAGSDATO": "24-01-2024",
    "ANTAL": "13",
    "STKPRIS": "483.83",
    "STKAFREGNSATS": "0.2219",
    "BELOEB": "1395.70",
    "VALUTA": "DKK",
    "SKAT": "0.00",
    "AFREGNBATCH": "6643"
  },
  {
    "TRANSNR": "27690",
    "TRANSTYPE": "GarGlobal",
    "KONTO": "AUTH-0215",
    "AFTALE": "AFT-2024-017",
    "ARTNR": "978-87-4303-407-0",
    "KANAL": "Lydbog",
    "PRISGRUPPE": "Special",
    "VILKAR": "B",
    "BILAGSNR": "79813",
    "BILAGSDATO": "26-01-2024",
    "ANTAL": "8",
    "STKPRIS": "426.58",
    "STKAFREGNSATS": "0.1574",
    "BELOEB": "537.15",
    "VALUTA": "DKK",
    "SKAT": "0.00",
    "AFREGNBATCH": "6643"
  },
  {
    "TRANSNR": "27691",
    "TRANSTYPE": "Salg",
    "KONTO": "AUTH-0215",
    "AFTALE": "AFT-2024-017",
    "ARTNR": "978-87-7384-966-8",
    "KANAL": "Online",
    "PRISGRUPPE": "Special",
    "VILKAR": "A",
    "BILAGSNR": "81384",
    "BILAGSDATO": "15-02-2024",
    "ANTAL": "613",
    "STKPRIS": "358.39",
    "STKAFREGNSATS": "0.1049",
    "BELOEB": "23045.80",
    "VALUTA": "DKK",
    "SKAT": "0.00",
    "AFREGNBATCH": "6643"
  },
  {
    "TRANSNR": "27692",
    "TRANSTYPE": "Salg",
    "KONTO": "AUTH-0215",
    "AFTALE": "AFT-2024-017",
    "ARTNR": "978-87-6041-809-9",
    "KANAL": "E-bog",
    "PRISGRUPPE": "Indbundet",
    "VILKAR": "D",
    "BILAGSNR": "79180",
    "BILAGSDATO": "02-01-2024",
    "ANTAL": "236",
    "STKPRIS": "91.18",
    "STKAFREGNSATS": "0.1445",
    "BELOEB": "3109.42",
    "VALUTA": "DKK",
    "SKAT": "0.00",
    "AFREGNBATCH": "6643"
  },
  {
    "TRANSNR": "27693",
    "TRANSTYPE": "Salg",
    "KONTO": "AUTH-0215",
    "AFTALE": "AFT-2024-017",
    "ARTNR": "978-87-3416-762-6",
    "KANAL": "E-bog",
    "PRISGRUPPE": "Digital",
    "VILKAR": "A",
    "BILAGSNR": "75879",
    "BILAGSDATO": "06-01-2024",
    "ANTAL": "553",
    "STKPRIS": "450.29",
    "STKAFREGNSATS": "0.0598",
    "BELOEB": "14890.82",
    "VALUTA": "DKK",
    "SKAT": "0.00",
    "AFREGNBATCH": "6643"
  },
  {
    "TRANSNR": "27694",
    "TRANSTYPE": "Salg",
    "KONTO": "AUTH-0215",
    "AFTALE": "AFT-2024-017",
    "ARTNR": "978-87-2837-413-9",
    "KANAL": "Online",
    "PRISGRUPPE": "Digital",
    "VILKAR": "B",
    "BILAGSNR": "58940",
    "BILAGSDATO": "08-01-2024",
    "ANTAL": "1957",
    "STKPRIS": "226.30",
    "STKAFREGNSATS": "0.1667",
    "BELOEB": "73826.28",
    "VALUTA": "DKK",
    "SKAT": "0.00",
    "AFREGNBATCH": "6643"
  },
  {
    "TRANSNR": "27695",
    "TRANSTYPE": "Korrektion",
    "KONTO": "AUTH-0215",
    "AFTALE": "AFT-2024-017",
    "ARTNR": "",
    "KANAL": "Bibliotek",
    "PRISGRUPPE": "Special",
    "VILKAR": "D",
    "BILAGSNR": "75088",
    "BILAGSDATO": "02-01-2024",
    "ANTAL": "875",
    "STKPRIS": "489.96",
    "STKAFREGNSATS": "0.0926",
    "BELOEB": "39699.01",
    "VALUTA": "NOK",
    "SKAT": "0.00",
    "AFREGNBATCH": "6643"
  },
  {
    "TRANSNR": "27696",
    "TRANSTYPE": "Salg",
    "KONTO": "AUTH-0215",
    "AFTALE": "AFT-2024-017",
    "ARTNR": "978-87-4128-345-6",
    "KANAL": "Subskription",
    "PRISGRUPPE": "Klassiker",
    "VILKAR": "C",
    "BILAGSNR": "85750",
    "BILAGSDATO": "31-12-2023",
    "ANTAL": "1353",
    "STKPRIS": "137.34",
    "STKAFREGNSATS": "0.0794",
    "BELOEB": "14754.19",
    "VALUTA": "DKK",
    "SKAT": "0.00",
    "AFREGNBATCH": "6643"
  },
  {
    "TRANSNR": "27697",
    "TRANSTYPE": "Korrektion",
    "KONTO": "AUTH-0215",
    "AFTALE": "AFT-2024-017",
    "ARTNR": "978-87-0185-247-0",
    "KANAL": "Boghandel",
    "PRISGRUPPE": "Pocket",
    "VILKAR": "D",
    "BILAGSNR": "81708",
    "BILAGSDATO": "27-12-2023",
    "ANTAL": "830",
    "STKPRIS": "180.22",
    "STKAFREGNSATS": "0.0987",
    "BELOEB": "14763.80",
    "VALUTA": "DKK",
    "SKAT": "0.00",
    "AFREGNBATCH": "6643"
  },
  {
    "TRANSNR": "27698",
    "TRANSTYPE": "Royalty",
    "KONTO": "AUTH-0215",
    "AFTALE": "AFT-2024-017",
    "ARTNR": "",
    "KANAL": "Bibliotek",
    "PRISGRUPPE": "Pocket",
    "VILKAR": "C",
    "BILAGSNR": "78148",
    "BILAGSDATO": "05-02-2024",
    "ANTAL": "920",
    "STKPRIS": "213.00",
    "STKAFREGNSATS": "0.0826",
    "BELOEB": "16186.30",
    "VALUTA": "DKK",
    "SKAT": "0.00",
    "AFREGNBATCH": "6643"
  },
  {
    "TRANSNR": "27699",
    "TRANSTYPE": "Salg",
    "KONTO": "AUTH-0215",
    "AFTALE": "AFT-2024-017",
    "ARTNR": "978-87-9144-256-8",
    "KANAL": "Online",
    "PRISGRUPPE": "Pocket",
    "VILKAR": "D",
    "BILAGSNR": "71141",
    "BILAGSDATO": "28-12-2023",
    "ANTAL": "1632",
    "STKPRIS": "315.33",
    "STKAFREGNSATS": "0.0893",
    "BELOEB": "45955.44",
    "VALUTA": "DKK",
    "SKAT": "0.00",
    "AFREGNBATCH": "6643"
  },
  {
    "TRANSNR": "27700",
    "TRANSTYPE": "Forskud",
    "KONTO": "AUTH-0215",
    "AFTALE": "AFT-2024-017",
    "ARTNR": "",
    "KANAL": "Bibliotek",
    "PRISGRUPPE": "Digital",
    "VILKAR": "C",
    "BILAGSNR": "63129",
    "BILAGSDATO": "09-01-2024",
    "ANTAL": "94",
    "STKPRIS": "250.54",
    "STKAFREGNSATS": "0.2343",
    "BELOEB": "5517.94",
    "VALUTA": "DKK",
    "SKAT": "0.00",
    "AFREGNBATCH": "6643"
  },
  {
    "TRANSNR": "27701",
    "TRANSTYPE": "Salg",
    "KONTO": "AUTH-0215",
    "AFTALE": "AFT-2024-017",
    "ARTNR": "978-87-8605-303-8",
    "KANAL": "Online",
    "PRISGRUPPE": "Standard",
    "VILKAR": "A",
    "BILAGSNR": "84774",
    "BILAGSDATO": "26-01-2024",
    "ANTAL": "1219",
    "STKPRIS": "534.38",
    "STKAFREGNSATS": "0.2456",
    "BELOEB": "159986.10",
    "VALUTA": "DKK",
    "SKAT": "0.00",
    "AFREGNBATCH": "6643"
  },
  {
    "TRANSNR": "27702",
    "TRANSTYPE": "Salg",
    "KONTO": "AUTH-0215",
    "AFTALE": "AFT-2024-017",
    "ARTNR": "978-87-8819-448-7",
    "KANAL": "Online",
    "PRISGRUPPE": "Lydbog",
    "VILKAR": "A",
    "BILAGSNR": "97965",
    "BILAGSDATO": "20-12-2023",
    "ANTAL": "1972",
    "STKPRIS": "577.34",
    "STKAFREGNSATS": "0.1551",
    "BELOEB": "176583.60",
    "VALUTA": "DKK",
    "SKAT": "0.00",
    "AFREGNBATCH": "6643"
  },
  {
    "TRANSNR": "27703",
    "TRANSTYPE": "Salg",
    "KONTO": "AUTH-0215",
    "AFTALE": "AFT-2024-017",
    "ARTNR": "978-87-2500-263-9",
    "KANAL": "Eksport",
    "PRISGRUPPE": "Standard",
    "VILKAR": "D",
    "BILAGSNR": "93900",
    "BILAGSDATO": "09-02-2024",
    "ANTAL": "716",
    "STKPRIS": "234.35",
    "STKAFREGNSATS": "0.2169",
    "BELOEB": "36394.65",
    "VALUTA": "DKK",
    "SKAT": "0.00",
    "AFREGNBATCH": "6643"
  }
]