[
  {
    "TRANSNR": "26895",
    "TRANSTYPE": "Frieksp",
    "KONTO": "AUTH-1506",
    "AFTALE": "AFT-2019-077",
    "ARTNR": "978-87-9085-950-3",
    "KANAL": "Boghandel",
    "PRISGRUPPE": "Special",
    "VILKAR": "D",
    "BILAGSNR": "84704",
    "BILAGSDATO": "29-04-2022",
    "ANTAL": "1064",
    "STKPRIS": "123.85",
    "STKAFREGNSATS": "0.1468",
    "BELOEB": "19344.78",
    "VALUTA": "DKK",
    "SKAT": "0.00",
    "AFREGNBATCH": "1728"
  },
  {
    "TRANSNR": "26896",
    "TRANSTYPE": "Salg",
    "KONTO": "AUTH-1506",
    "AFTALE": "AFT-2019-077",
    "ARTNR": "978-87-7156-267-5",
    "KANAL": "Eksport",
    "PRISGRUPPE": "Klassiker",
    "VILKAR": "D",
    "BILAGSNR": "80527",
    "BILAGSDATO": "06-05-2022",
    "ANTAL": "1218",
    "STKPRIS": "98.82",
    "STKAFREGNSATS": "0.1962",
    "BELOEB": "23615.17",
    "VALUTA": "SEK",
    "SKAT": "0.00",
    "AFREGNBATCH": "1728"
  },
  {
    "TRANSNR": "26897",
    "TRANSTYPE": "Salg",
    "KONTO": "AUTH-1506",
    "AFTALE": "AFT-2019-077",
    "ARTNR": "978-87-6856-656-3",
    "KANAL": "Boghandel",
    "PRISGRUPPE": "Digital",
    "VILKAR": "D",
    "BILAGSNR": "60820",
    "BILAGSDATO": "11-04-2022",
    "ANTAL": "1482",
    "STKPRIS": "439.25",
    "STKAFREGNSATS": "0.0841",
    "BELOEB": "54746.45",
    "VALUTA": "DKK",
    "SKAT": "0.00",
    "AFREGNBATCH": "1728"
  },
  {
    "TRANSNR": "26898",
    "TRANSTYPE": "Salg",
    "KONTO": "AUTH-1506",
    "AFTALE": "AFT-2019-077",
    "ARTNR": "978-87-4937-325-8",
    "KANAL": "Eksport",
    "PRISGRUPPE": "Lydbog",
    "VILKAR": "B",
    "BILAGSNR": "76774",
    "BILAGSDATO": "16-04-2022",
    "ANTAL": "836",
    "STKPRIS": "338.09",
    "STKAFREGNSATS": "0.2432",
    "BELOEB": "68738.84",
    "VALUTA": "DKK",
    "SKAT": "0.00",
    "AFREGNBATCH": "1728"
  },
  {
    "TRANSNR": "26899",
    "TRANSTYPE": "Afgift",
    "KONTO": "AUTH-1506",
    "AFTALE": "AFT-2019-077",
    "ARTNR": "978-87-6681-583-0",
    "KANAL": "Online",
    "PRISGRUPPE": "Klassiker",
    "VILKAR": "B",
    "BILAGSNR": "92526",
    "BILAGSDATO": "19-03-2022",
    "ANTAL": "648",
    "STKPRIS": "386.35",
    "STKAFREGNSATS": "0.1656",
    "BELOEB": "41458.75",
    "VALUTA": "DKK",
    "SKAT": "0.00",
    "AFREGNBATCH": "1728"
  },
  {
    "TRANSNR": "26900",
    "TRANSTYPE": "Salg",
    "KONTO": "AUTH-1506",
    "AFTALE": "AFT-2019-077",
    "ARTNR": "978-87-0881-456-3",
    "KANAL": "Online",
    "PRISGRUPPE": "Klassiker",
    "VILKAR": "B",
    "BILAGSNR": "52544",
    "BILAGSDATO": "05-04-2022",
    "ANTAL": "1496",
    "STKPRIS": "301.33",
    "STKAFREGNSATS": "0.234",
    "BELOEB": "105484.79",
    "VALUTA": "SEK",
    "SKAT": "0.00",
    "AFREGNBATCH": "1728"
  },
  {
    "TRANSNR": "26901",
    "TRANSTYPE": "Salg",
    "KONTO": "AUTH-1506",
    "AFTALE": "AFT-2019-077",
    "ARTNR": "978-87-3894-469-8",
    "KANAL": "Eksport",
    "PRISGRUPPE": "Special",
    "VILKAR": "C",
    "BILAGSNR": "65318",
    "BILAGSDATO": "31-03-2022",
    "ANTAL": "1474",
    "STKPRIS": "219.49",
    "STKAFREGNSATS": "0.1754",
    "BELOEB": "56746.86",
    "VALUTA": "DKK",
    "SKAT": "0.00",
    "AFREGNBATCH": "1728"
  },
  {
    "TRANSNR": "26902",
    "TRANSTYPE": "Salg",
    "KONTO": "AUTH-1506",
    "AFTALE": "AFT-2019-077",
    "ARTNR": "978-87-8458-043-7",
    "KANAL": "Boghandel",
    "PRISGRUPPE": "Special",
    "VILKAR": "B",
    "BILAGSNR": "61191",
    "BILAGSDATO": "27-04-2022",
    "ANTAL": "1142",
    "STKPRIS": "406.78",
    "STKAFREGNSATS": "0.164",
    "BELOEB": "76185.01",
    "VALUTA": "DKK",
    "SKAT": "0.00",
    "AFREGNBATCH": "1728"
  },
  {
    "TRANSNR": "26903",
    "TRANSTYPE": "Afgift",
    "KONTO": "AUTH-1506",
    "AFTALE": "AFT-2019-077",
    "ARTNR": "978-87-9446-993-7",
    "KANAL": "Subskription",
    "PRISGRUPPE": "Indbundet",
    "VILKAR": "C",
    "BILAGSNR": "84740",
    "BILAGSDATO": "14-05-2022",
    "ANTAL": "799",
    "STKPRIS": "353.26",
    "STKAFREGNSATS": "0.2335",
    "BELOEB": "65906.48",
    "VALUTA": "DKK",
    "SKAT": "0.00",
    "AFREGNBATCH": "1728"
  },
  {
    "TRANSNR": "26904",
    "TRANSTYPE": "Salg",
    "KONTO": "AUTH-1506",
    "AFTALE": "AFT-2019-077",
    "ARTNR": "978-87-6050-334-4",
    "KANAL": "Lydbog",
    "PRISGRUPPE": "Digital",
    "VILKAR": "D",
    "BILAGSNR": "98959",
    "BILAGSDATO": "09-05-2022",
    "ANTAL": "542",
    "STKPRIS": "299.22",
    "STKAFREGNSATS": "0.1298",
    "BELOEB": "21050.61",
    "VALUTA": "DKK",
    "SKAT": "0.00",
    "AFREGNBATCH": "1728"
  },
  {
    "TRANSNR": "26905",
    "TRANSTYPE": "Forskud",
    "KONTO": "AUTH-1506",
    "AFTALE": "AFT-2019-077",
    "ARTNR": "978-87-0789-131-2",
    "KANAL": "Boghandel",
    "PRISGRUPPE": "Special",
    "VILKAR": "D",
    "BILAGSNR": "54084",
    "BILAGSDATO": "27-04-2022",
    "ANTAL": "1209",
    "STKPRIS": "579.24",
    "STKAFREGNSATS": "0.176",
    "BELOEB": "123253.00",
    "VALUTA": "DKK",
    "SKAT": "0.00",
    "AFREGNBATCH": "1728"
  },
  {
    "TRANSNR": "26906",
    "TRANSTYPE": "Salg",
    "KONTO": "AUTH-1506",
    "AFTALE": "AFT-2019-077",
    "ARTNR": "978-87-8408-163-7",
    "KANAL": "Online",
    "PRISGRUPPE": "Digital",
    "VILKAR": "B",
    "BILAGSNR": "90463",
    "BILAGSDATO": "22-04-2022",
    "ANTAL": "330",
    "STKPRIS": "308.67",
    "STKAFREGNSATS": "0.1567",
    "BELOEB": "15961.63",
    "VALUTA": "DKK",
    "SKAT": "0.00",
    "AFREGNBATCH": "1728"
  },
  {
    "TRANSNR": "26907",
    "TRANSTYPE": "Salg",
    "KONTO": "AUTH-1506",
    "AFTALE": "AFT-2019-077",
    "ARTNR": "978-87-9539-596-9",
    "KANAL": "Eksport",
    "PRISGRUPPE": "Digital",
    "VILKAR": "A",
    "BILAGSNR": "90165",
    "BILAGSDATO": "26-04-2022",
    "ANTAL": "1228",
    "STKPRIS": "598.42",
    "STKAFREGNSATS": "0.102",
    "BELOEB": "74955.70",
    "VALUTA": "DKK",
    "SKAT": "0.00",
    "AFREGNBATCH": "1728"
  },
  {
    "TRANSNR": "26908",
    "TRANSTYPE": "Salg",
    "KONTO": "AUTH-1506",
    "AFTALE": "AFT-2019-077",
    "ARTNR": "978-87-4615-626-7",
    "KANAL": "E-bog",
    "PRISGRUPPE": "Digital",
    "VILKAR": "C",
    "BILAGSNR": "83288",
    "BILAGSDATO": "09-04-2022",
    "ANTAL": "358",
    "STKPRIS": "496.13",
    "STKAFREGNSATS": "0.1795",
    "BELOEB": "31881.81",
    "VALUTA": "DKK",
    "SKAT": "0.00",
    "AFREGNBATCH": "1728"
  }
]