[
  {
    "TRANSNR": "28795",
    "TRANSTYPE": "Salg",
    "KONTO": "AUTH-0215",
    "AFTALE": "AFT-2020-099",
    "ARTNR": "978-87-6186-504-5",
    "KANAL": "Lydbog",
    "PRISGRUPPE": "Pocket",
    "VILKAR": "A",
    "BILAGSNR": "72000",
    "BILAGSDATO": "2023-03-07",
    "ANTAL": "1945",
    "STKPRIS": "562.01",
    "STKAFREGNSATS": "0.0752",
    "BELOEB": "82201.83",
    "VALUTA": "DKK",
    "SKAT": "0.00",
    "AFREGNBATCH": "7287"
  },
  {
    "TRANSNR": "28796",
    "TRANSTYPE": "Salg",
    "KONTO": "AUTH-0215",
    "AFTALE": "AFT-2020-099",
    "ARTNR": "978-87-2773-940-3",
    "KANAL": "Bibliotek",
    "PRISGRUPPE": "Digital",
    "VILKAR": "A",
    "BILAGSNR": "83366",
    "BILAGSDATO": "2023-03-22",
    "ANTAL": "1769",
    "STKPRIS": "234.54",
    "STKAFREGNSATS": "0.1845",
    "BELOEB": "76549.28",
    "VALUTA": "DKK",
    "SKAT": "0.00",
    "AFREGNBATCH": "7287"
  },
  {
    "TRANSNR": "28797",
    "TRANSTYPE": "Salg",
    "KONTO": "AUTH-0215",
    "AFTALE": "AFT-2020-099",
    "ARTNR": "978-87-3831-415-6",
    "KANAL": "Boghandel",
    "PRISGRUPPE": "Pocket",
    "VILKAR": "B",
    "BILAGSNR": "71700",
    "BILAGSDATO": "2023-03-10",
    "ANTAL": "1661",
    "STKPRIS": "478.82",
    "STKAFREGNSATS": "0.1492",
    "BELOEB": "118542.80",
    "VALUTA": "EUR",
    "SKAT": "0.00",
    "AFREGNBATCH": "7287"
  },
  {
    "TRANSNR": "28798",
    "TRANSTYPE": "Salg",
    "KONTO": "AUTH-0215",
    "AFTALE": "AFT-2020-099",
    "ARTNR": "978-87-1495-852-7",
    "KANAL": "Lydbog",
    "PRISGRUPPE": "Digital",
    "VILKAR": "B",
    "BILAGSNR": "99817",
    "BILAGSDATO": "2023-04-11",
    "ANTAL": "453",
    "STKPRIS": "535.28",
    "STKAFREGNSATS": "0.0592",
    "BELOEB": "14354.92",
    "VALUTA": "DKK",
    "SKAT": "0.00",
    "AFREGNBATCH": "7287"
  },
  {
    "TRANSNR": "28799",
    "TRANSTYPE": "Retur",
    "KONTO": "AUTH-0215",
    "AFTALE": "AFT-2020-099",
    "ARTNR": "978-87-8195-684-6",
    "KANAL": "E-bog",
    "PRISGRUPPE": "Lydbog",
    "VILKAR": "C",
    "BILAGSNR": "75354",
    "BILAGSDATO": "2023-03-21",
    "ANTAL": "-1402",
    "STKPRIS": "122.42",
    "STKAFREGNSATS": "0.1718",
    "BELOEB": "-29486.52",
    "VALUTA": "DKK",
    "SKAT": "0.00",
    "AFREGNBATCH": "7287"
  },
  {
    "TRANSNR": "28800",
    "TRANSTYPE": "Salg",
    "KONTO": "AUTH-0215",
    "AFTALE": "AFT-2020-099",
    "ARTNR": "978-87-6209-421-5",
    "KANAL": "Eksport",
    "PRISGRUPPE": "Special",
    "VILKAR": "C",
    "BILAGSNR": "62574",
    "BILAGSDATO": "2023-04-18",
    "ANTAL": "215",
    "STKPRIS": "153.78",
    "STKAFREGNSATS": "0.1566",
    "BELOEB": "5060.58",
    "VALUTA": "DKK",
    "SKAT": "0.00",
    "AFREGNBATCH": "7287"
  },
  {
    "TRANSNR": "28801",
    "TRANSTYPE": "Salg",
    "KONTO": "AUTH-0215",
    "AFTALE": "AFT-2020-099",
    "ARTNR": "978-87-3753-546-0",
    "KANAL": "Online",
    "PRISGRUPPE": "Indbundet",
    "VILKAR": "A",
    "BILAGSNR": "82640",
    "BILAGSDATO": "2023-04-26",
    "ANTAL": "672",
    "STKPRIS": "452.62",
    "STKAFREGNSATS": "0.0844",
    "BELOEB": "25671.16",
    "VALUTA": "DKK",
    "SKAT": "0.00",
    "AFREGNBATCH": "7287"
  },
  {
    "TRANSNR": "28802",
    "TRANSTYPE": "Salg",
    "KONTO": "AUTH-0215",
    "AFTALE": "AFT-2020-099",
    "ARTNR": "978-87-0854-401-9",
    "KANAL": "Online",
    "PRISGRUPPE": "Klassiker",
    "VILKAR": "A",
    "BILAGSNR": "96386",
    "BILAGSDATO": "2023-04-03",
    "ANTAL": "1493",
    "STKPRIS": "494.24",
    "STKAFREGNSATS": "0.1248",
    "BELOEB": "92089.96",
    "VALUTA": "DKK",
    "SKAT": "0.00",
    "AFREGNBATCH": "7287"
  },
  {
    "TRANSNR": "28803",
    "TRANSTYPE": "Salg",
    "KONTO": "AUTH-0215",
    "AFTALE": "AFT-2020-099",
    "ARTNR": "978-87-5641-368-8",
    "KANAL": "Boghandel",
    "PRISGRUPPE": "Digital",
    "VILKAR": "D",
    "BILAGSNR": "91198",
    "BILAGSDATO": "2023-04-30",
    "ANTAL": "1155",
    "STKPRIS": "67.62",
    "STKAFREGNSATS": "0.2456",
    "BELOEB": "19181.63",
    "VALUTA": "DKK",
    "SKAT": "0.00",
    "AFREGNBATCH": "7287"
  },
  {
    "TRANSNR": "28804",
    "TRANSTYPE": "Salg",
    "KONTO": "AUTH-0215",
    "AFTALE": "AFT-2020-099",
    "ARTNR": "978-87-2317-579-3",
    "KANAL": "Eksport",
    "PRISGRUPPE": "Lydbog",
    "VILKAR": "D",
    "BILAGSNR": "75366",
    "BILAGSDATO": "2023-04-19",
    "ANTAL": "1125",
    "STKPRIS": "228.17",
    "STKAFREGNSATS": "0.0526",
    "BELOEB": "13501.96",
    "VALUTA": "DKK",
    "SKAT": "0.00",
    "AFREGNBATCH": "7287"
  },
  {
    "TRANSNR": "28805",
    "TRANSTYPE": "Salg",
    "KONTO": "AUTH-0215",
    "AFTALE": "AFT-2020-099",
    "ARTNR": "978-87-7971-206-5",
    "KANAL": "Online",
    "PRISGRUPPE": "Klassiker",
    "VILKAR": "A",
    "BILAGSNR": "58380",
    "BILAGSDATO": "2023-04-07",
    "ANTAL": "1733",
    "STKPRIS": "248.04",
    "STKAFREGNSATS": "0.1933",
    "BELOEB": "83182.91",
    "VALUTA": "DKK",
    "SKAT": "0.00",
    "AFREGNBATCH": "7287"
  },
  {
    "TRANSNR": "28806",
    "TRANSTYPE": "Forskud",
    "KONTO": "AUTH-0215",
    "AFTALE": "AFT-2020-099",
    "ARTNR": "978-87-8008-805-0",
    "KANAL": "E-bog",
    "PRISGRUPPE": "Klassiker",
    "VILKAR": "A",
    "BILAGSNR": "60245",
    "BILAGSDATO": "2023-03-12",
    "ANTAL": "1047",
    "STKPRIS": "328.42",
    "STKAFREGNSATS": "0.0867",
    "BELOEB": "29812.29",
    "VALUTA": "DKK",
    "SKAT": "0.00",
    "AFREGNBATCH": "7287"
  },
  {
    "TRANSNR": "28807",
    "TRANSTYPE": "Retur",
    "KONTO": "AUTH-0215",
    "AFTALE": "AFT-2020-099",
    "ARTNR": "978-87-4257-983-1",
    "KANAL": "Eksport",
    "PRISGRUPPE": "Special",
    "VILKAR": "D",
    "BILAGSNR": "66788",
    "BILAGSDATO": "2023-04-03",
    "ANTAL": "-821",
    "STKPRIS": "539.84",
    "STKAFREGNSATS": "0.1579",
    "BELOEB": "-70271.73",
    "VALUTA": "DKK",
    "SKAT": "0.00",
    "AFREGNBATCH": "7287"
  },
  {
    "TRANSNR": "28808",
    "TRANSTYPE": "Bonus",
    "KONTO": "AUTH-0215",
    "AFTALE": "AFT-2020-099",
    "ARTNR": "978-87-9327-202-6",
    "KANAL": "Boghandel",
    "PRISGRUPPE": "Lydbog",
    "VILKAR": "B",
    "BILAGSNR": "89049",
    "BILAGSDATO": "2023-04-10",
    "ANTAL": "741",
    "STKPRIS": "312.79",
    "STKAFREGNSATS": "0.085",
    "BELOEB": "19701.08",
    "VALUTA": "DKK",
    "SKAT": "0.00",
    "AFREGNBATCH": "7287"
  },
  {
    "TRANSNR": "28809",
    "TRANSTYPE": "Salg",
    "KONTO": "AUTH-0215",
    "AFTALE": "AFT-2020-099",
    "ARTNR": "978-87-9984-592-7",
    "KANAL": "E-bog",
    "PRISGRUPPE": "Special",
    "VILKAR": "D",
    "BILAGSNR": "65478",
    "BILAGSDATO": "2023-03-19",
    "ANTAL": "798",
    "STKPRIS": "309.17",
    "STKAFREGNSATS": "0.1573",
    "BELOEB": "38575.78",
    "VALUTA": "DKK",
    "SKAT": "0.00",
    "AFREGNBATCH": "7287"
  },
  {
    "TRANSNR": "28810",
    "TRANSTYPE": "Korrektion",
    "KONTO": "AUTH-0215",
    "AFTALE": "AFT-2020-099",
    "ARTNR": "978-87-6095-695-9",
    "KANAL": "Boghandel",
    "PRISGRUPPE": "Klassiker",
    "VILKAR": "C",
    "BILAGSNR": "59416",
    "BILAGSDATO": "2023-05-01",
    "ANTAL": "82",
    "STKPRIS": "554.92",
    "STKAFREGNSATS": "0.1803",
    "BELOEB": "8204.27",
    "VALUTA": "DKK",
    "SKAT": "0.00",
    "AFREGNBATCH": "7287"
  },
  {
    "TRANSNR": "28811",
    "TRANSTYPE": "Retur",
    "KONTO": "AUTH-0215",
    "AFTALE": "AFT-2020-099",
    "ARTNR": "978-87-9430-286-9",
    "KANAL": "Boghandel",
    "PRISGRUPPE": "Klassiker",
    "VILKAR": "B",
    "BILAGSNR": "75121",
    "BILAGSDATO": "2023-03-14",
    "ANTAL": "-532",
    "STKPRIS": "413.81",
    "STKAFREGNSATS": "0.1936",
    "BELOEB": "-42494.81",
    "VALUTA": "DKK",
    "SKAT": "0.00",
    "AFREGNBATCH": "7287"
  },
  {
    "TRANSNR": "28812",
    "TRANSTYPE": "Retur",
    "KONTO": "AUTH-0215",
    "AFTALE": "AFT-2020-099",
    "ARTNR": "978-87-3036-599-6",
    "KANAL": "Lydbog",
    "PRISGRUPPE": "Klassiker",
    "VILKAR": "A",
    "BILAGSNR": "99419",
    "BILAGSDATO": "2023-03-19",
    "ANTAL": "-215",
    "STKPRIS": "456.69",
    "STKAFREGNSATS": "0.1667",
    "BELOEB": "-16661.86",
    "VALUTA": "DKK",
    "SKAT": "0.00",
    "AFREGNBATCH": "7287"
  },
  {
    "TRANSNR": "28813",
    "TRANSTYPE": "Salg",
    "KONTO": "AUTH-0215",
    "AFTALE": "AFT-2020-099",
    "ARTNR": "978-87-6653-718-3",
    "KANAL": "Lydbog",
    "PRISGRUPPE": "Digital",
    "VILKAR": "B",
    "BILAGSNR": "57330",
    "BILAGSDATO": "2023-03-24",
    "ANTAL": "1927",
    "STKPRIS": "445.68",
    "STKAFREGNSATS": "0.1041",
    "BELOEB": "89403.72",
    "VALUTA": "DKK",
    "SKAT": "0.00",
    "AFREGNBATCH": "7287"
  },
  {
    "TRANSNR": "28814",
    "TRANSTYPE": "Salg",
    "KONTO": "AUTH-0215",
    "AFTALE": "AFT-2020-099",
    "ARTNR": "978-87-0756-693-7",
    "KANAL": "Subskription",
    "PRISGRUPPE": "Digital",
    "VILKAR": "C",
    "BILAGSNR": "58819",
    "BILAGSDATO": "2023-03-22",
    "ANTAL": "1700",
    "STKPRIS": "78.70",
    "STKAFREGNSATS": "0.1497",
    "BELOEB": "20028.36",
    "VALUTA": "DKK",
    "SKAT": "0.00",
    "AFREGNBATCH": "7287"
  },
  {
    "TRANSNR": "28815",
    "TRANSTYPE": "Salg",
    "KONTO": "AUTH-0215",
    "AFTALE": "AFT-2020-099",
    "ARTNR": "978-87-3952-048-8",
    "KANAL": "Lydbog",
    "PRISGRUPPE": "Standard",
    "VILKAR": "A",
    "BILAGSNR": "88162",
    "BILAGSDATO": "2023-03-18",
    "ANTAL": "638",
    "STKPRIS": "360.09",
    "STKAFREGNSATS": "0.2432",
    "BELOEB": "55708.59",
    "VALUTA": "DKK",
    "SKAT": "0.00",
    "AFREGNBATCH": "7287"
  },
  {
    "TRANSNR": "28816",
    "TRANSTYPE": "Salg",
    "KONTO": "AUTH-0215",
    "AFTALE": "AFT-2020-099",
    "ARTNR": "978-87-2288-881-6",
    "KANAL": "Lydbog",
    "PRISGRUPPE": "Digital",
    "VILKAR": "A",
    "BILAGSNR": "89097",
    "BILAGSDATO": "2023-03-30",
    "ANTAL": "1307",
    "STKPRIS": "230.61",
    "STKAFREGNSATS": "0.1014",
    "BELOEB": "30562.70",
    "VALUTA": "DKK",
    "SKAT": "0.00",
    "AFREGNBATCH": "7287"
  },
  {
    "TRANSNR": "28817",
    "TRANSTYPE": "Diverse",
    "KONTO": "AUTH-0215",
    "AFTALE": "AFT-2020-099",
    "ARTNR": "978-87-7022-843-5",
    "KANAL": "Boghandel",
    "PRISGRUPPE": "Special",
    "VILKAR": "A",
    "BILAGSNR": "98622",
    "BILAGSDATO": "2023-03-17",
    "ANTAL": "290",
    "STKPRIS": "88.01",
    "STKAFREGNSATS": "0.0869",
    "BELOEB": "2123.61",
    "VALUTA": "DKK",
    "SKAT": "0.00",
    "AFREGNBATCH": "7287"
  },
  {
    "TRANSNR": "28818",
    "TRANSTYPE": "Salg",
    "KONTO": "AUTH-0215",
    "AFTALE": "AFT-2020-099",
    "ARTNR": "978-87-5903-410-1",
    "KANAL": "Boghandel",
    "PRISGRUPPE": "Pocket",
    "VILKAR": "C",
    "BILAGSNR": "89111",
    "BILAGSDATO": "2023-03-12",
    "ANTAL": "683",
    "STKPRIS": "597.65",
    "STKAFREGNSATS": "0.1021",
    "BELOEB": "41676.70",
    "VALUTA": "DKK",
    "SKAT": "0.00",
    "AFREGNBATCH": "7287"
  },
  {
    "TRANSNR": "28819",
    "TRANSTYPE": "Salg",
    "KONTO": "AUTH-0215",
    "AFTALE": "AFT-2020-099",
    "ARTNR": "978-87-5006-031-4",
    "KANAL": "Online",
    "PRISGRUPPE": "Lydbog",
    "VILKAR": "B",
    "BILAGSNR": "72247",
    "BILAGSDATO": "2023-04-18",
    "ANTAL": "1092",
    "STKPRIS": "180.71",
    "STKAFREGNSATS": "0.248",
    "BELOEB": "48939.16",
    "VALUTA": "DKK",
    "SKAT": "0.00",
    "AFREGNBATCH": "7287"
  },
  {
    "TRANSNR": "28820",
    "TRANSTYPE": "Korrektion",
    "KONTO": "AUTH-0215",
    "AFTALE": "AFT-2020-099",
    "ARTNR": "978-87-5645-165-9",
    "KANAL": "Boghandel",
    "PRISGRUPPE": "Lydbog",
    "VILKAR": "A",
    "BILAGSNR": "80831",
    "BILAGSDATO": "2023-04-10",
    "ANTAL": "261",
    "STKPRIS": "490.49",
    "STKAFREGNSATS": "0.1843",
    "BELOEB": "23593.70",
    "VALUTA": "DKK",
    "SKAT": "0.00",
    "AFREGNBATCH": "7287"
  },
  {
    "TRANSNR": "28821",
    "TRANSTYPE": "Retur",
    "KONTO": "AUTH-0215",
    "AFTALE": "AFT-2020-099",
    "ARTNR": "978-87-9736-135-1",
    "KANAL": "Online",
    "PRISGRUPPE": "Indbundet",
    "VILKAR": "C",
    "BILAGSNR": "79203",
    "BILAGSDATO": "2023-03-16",
    "ANTAL": "-316",
    "STKPRIS": "179.74",
    "STKAFREGNSATS": "0.1543",
    "BELOEB": "-8763.91",
    "VALUTA": "DKK",
    "SKAT": "0.00",
    "AFREGNBATCH": "7287"
  },
  {
    "TRANSNR": "28822",
    "TRANSTYPE": "Retur",
    "KONTO": "AUTH-0215",
    "AFTALE": "AFT-2020-099",
    "ARTNR": "978-87-4265-874-1",
    "KANAL": "Bibliotek",
    "PRISGRUPPE": "Klassiker",
    "VILKAR": "D",
    "BILAGSNR": "50255",
    "BILAGSDATO": "2023-04-22",
    "ANTAL": "-416",
    "STKPRIS": "324.67",
    "STKAFREGNSATS": "0.1445",
    "BELOEB": "-19516.56",
    "VALUTA": "DKK",
    "SKAT": "0.00",
    "AFREGNBATCH": "7287"
  },
  {
    "TRANSNR": "28823",
    "TRANSTYPE": "Salg",
    "KONTO": "AUTH-0215",
    "AFTALE": "AFT-2020-099",
    "ARTNR": "978-87-5988-087-6",
    "KANAL": "Boghandel",
    "PRISGRUPPE": "Standard",
    "VILKAR": "D",
    "BILAGSNR": "60846",
    "BILAGSDATO": "2023-03-08",
    "ANTAL": "1025",
    "STKPRIS": "234.42",
    "STKAFREGNSATS": "0.068",
    "BELOEB": "16339.07",
    "VALUTA": "DKK",
    "SKAT": "0.00",
    "AFREGNBATCH": "7287"
  },
  {
    "TRANSNR": "28824",
    "TRANSTYPE": "Royalty",
    "KONTO": "AUTH-0215",
    "AFTALE": "AFT-2020-099",
    "ARTNR": "978-87-2371-509-8",
    "KANAL": "E-bog",
    "PRISGRUPPE": "Digital",
    "VILKAR": "B",
    "BILAGSNR": "52365",
    "BILAGSDATO": "2023-03-22",
    "ANTAL": "881",
    "STKPRIS": "410.05",
    "STKAFREGNSATS": "0.1015",
    "BELOEB": "36667.29",
    "VALUTA": "DKK",
    "SKAT": "0.00",
    "AFREGNBATCH": "7287"
  },
  {
    "TRANSNR": "28825",
    "TRANSTYPE": "Salg",
    "KONTO": "AUTH-0215",
    "AFTALE": "AFT-2020-099",
    "ARTNR": "978-87-7465-517-6",
    "KANAL": "E-bog",
    "PRISGRUPPE": "Digital",
    "VILKAR": "D",
    "BILAGSNR": "74164",
    "BILAGSDATO": "2023-04-15",
    "ANTAL": "1883",
    "STKPRIS": "212.78",
    "STKAFREGNSATS": "0.1793",
    "BELOEB": "71839.19",
    "VALUTA": "DKK",
    "SKAT": "0.00",
    "AFREGNBATCH": "7287"
  },
  {
    "TRANSNR": "28826",
    "TRANSTYPE": "Salg",
    "KONTO": "AUTH-0215",
    "AFTALE": "AFT-2020-099",
    "ARTNR": "978-87-9236-042-7",
    "KANAL": "Boghandel",
    "PRISGRUPPE": "Indbundet",
    "VILKAR": "D",
    "BILAGSNR": "72094",
    "BILAGSDATO": "2023-03-03",
    "ANTAL": "1966",
    "STKPRIS": "553.99",
    "STKAFREGNSATS": "0.2377",
    "BELOEB": "258889.61",
    "VALUTA": "DKK",
    "SKAT": "0.00",
    "AFREGNBATCH": "7287"
  },
  {
    "TRANSNR": "28827",
    "TRANSTYPE": "Salg",
    "KONTO": "AUTH-0215",
    "AFTALE": "AFT-2020-099",
    "ARTNR": "978-87-7404-356-0",
    "KANAL": "Bibliotek",
    "PRISGRUPPE": "Special",
    "VILKAR": "B",
    "BILAGSNR": "97584",
    "BILAGSDATO": "2023-03-23",
    "ANTAL": "1980",
    "STKPRIS": "530.55",
    "STKAFREGNSATS": "0.097",
    "BELOEB": "101897.43",
    "VALUTA": "DKK",
    "SKAT": "0.00",
    "AFREGNBATCH": "7287"
  },
  {
    "TRANSNR": "28828",
    "TRANSTYPE": "GarGlobalMod",
    "KONTO": "AUTH-0215",
    "AFTALE": "AFT-2020-099",
    "ARTNR": "978-87-0870-876-3",
    "KANAL": "Eksport",
    "PRISGRUPPE": "Special",
    "VILKAR": "D",
    "BILAGSNR": "74181",
    "BILAGSDATO": "2023-03-30",
    "ANTAL": "564",
    "STKPRIS": "439.90",
    "STKAFREGNSATS": "0.0832",
    "BELOEB": "20642.22",
    "VALUTA": "DKK",
    "SKAT": "0.00",
    "AFREGNBATCH": "7287"
  },
  {
    "TRANSNR": "28829",
    "TRANSTYPE": "Salg",
    "KONTO": "AUTH-0215",
    "AFTALE": "AFT-2020-099",
    "ARTNR": "978-87-0941-502-8",
    "KANAL": "E-bog",
    "PRISGRUPPE": "Pocket",
    "VILKAR": "B",
    "BILAGSNR": "90426",
    "BILAGSDATO": "2023-04-02",
    "ANTAL": "1850",
    "STKPRIS": "91.24",
    "STKAFREGNSATS": "0.1727",
    "BELOEB": "29122.50",
    "VALUTA": "DKK",
    "SKAT": "0.00",
    "AFREGNBATCH": "7287"
  },
  {
    "TRANSNR": "28830",
    "TRANSTYPE": "Salg",
    "KONTO": "AUTH-0215",
    "AFTALE": "AFT-2020-099",
    "ARTNR": "978-87-2482-038-8",
    "KANAL": "Boghandel",
    "PRISGRUPPE": "Special",
    "VILKAR": "D",
    "BILAGSNR": "85646",
    "BILAGSDATO": "2023-03-11",
    "ANTAL": "1320",
    "STKPRIS": "472.79",
    "STKAFREGNSATS": "0.2303",
    "BELOEB": "144013.18",
    "VALUTA": "EUR",
    "SKAT": "0.00",
    "AFREGNBATCH": "7287"
  },
  {
    "TRANSNR": "28831",
    "TRANSTYPE": "Salg",
    "KONTO": "AUTH-0215",
    "AFTALE": "AFT-2020-099",
    "ARTNR": "978-87-0192-736-9",
    "KANAL": "E-bog",
    "PRISGRUPPE": "Special",
    "VILKAR": "D",
    "BILAGSNR": "81962",
    "BILAGSDATO": "2023-04-12",
    "ANTAL": "89",
    "STKPRIS": "512.68",
    "STKAFREGNSATS": "0.1455",
    "BELOEB": "6323.45",
    "VALUTA": "DKK",
    "SKAT": "0.00",
    "AFREGNBATCH": "7287"
  },
  {
    "TRANSNR": "28832",
    "TRANSTYPE": "Salg",
    "KONTO": "AUTH-0215",
    "AFTALE": "AFT-2020-099",
    "ARTNR": "978-87-6353-972-2",
    "KANAL": "Bibliotek",
    "PRISGRUPPE": "Lydbog",
    "VILKAR": "D",
    "BILAGSNR": "72232",
    "BILAGSDATO": "2023-03-15",
    "ANTAL": "371",
    "STKPRIS": "490.57",
    "STKAFREGNSATS": "0.2199",
    "BELOEB": "40115.25",
    "VALUTA": "DKK",
    "SKAT": "0.00",
    "AFREGNBATCH": "7287"
  },
  {
    "TRANSNR": "28833",
    "TRANSTYPE": "Salg",
    "KONTO": "AUTH-0215",
    "AFTALE": "AFT-2020-099",
    "ARTNR": "978-87-0458-575-7",
    "KANAL": "Lydbog",
    "PRISGRUPPE": "Digital",
    "VILKAR": "C",
    "BILAGSNR": "95373",
    "BILAGSDATO": "2023-03-02",
    "ANTAL": "279",
    "STKPRIS": "92.31",
    "STKAFREGNSATS": "0.2379",
    "BELOEB": "6089.36",
    "VALUTA": "DKK",
    "SKAT": "0.00",
    "AFREGNBATCH": "7287"
  },
  {
    "TRANSNR": "28834",
    "TRANSTYPE": "Salg",
    "KONTO": "AUTH-0215",
    "AFTALE": "AFT-2020-099",
    "ARTNR": "978-87-7041-506-4",
    "KANAL": "E-bog",
    "PRISGRUPPE": "Special",
    "VILKAR": "B",
    "BILAGSNR": "84676",
    "BILAGSDATO": "2023-03-22",
    "ANTAL": "550",
    "STKPRIS": "332.02",
    "STKAFREGNSATS": "0.2225",
    "BELOEB": "40851.53",
    "VALUTA": "DKK",
    "SKAT": "0.00",
    "AFREGNBATCH": "7287"
  },
  {
    "TRANSNR": "28835",
    "TRANSTYPE": "Forskud",
    "KONTO": "AUTH-0215",
    "AFTALE": "AFT-2020-099",
    "ARTNR": "978-87-7943-753-1",
    "KANAL": "Subskription",
    "PRISGRUPPE": "Standard",
    "VILKAR": "C",
    "BILAGSNR": "60639",
    "BILAGSDATO": "2023-03-06",
    "ANTAL": "300",
    "STKPRIS": "314.96",
    "STKAFREGNSATS": "0.1259",
    "BELOEB": "11896.04",
    "VALUTA": "DKK",
    "SKAT": "0.00",
    "AFREGNBATCH": "7287"
  },
  {
    "TRANSNR": "28836",
    "TRANSTYPE": "Retur",
    "KONTO": "AUTH-0215",
    "AFTALE": "AFT-2020-099",
    "ARTNR": "978-87-6823-569-8",
    "KANAL": "Subskription",
    "PRISGRUPPE": "Lydbog",
    "VILKAR": "A",
    "BILAGSNR": "75100",
    "BILAGSDATO": "2023-03-26",
    "ANTAL": "-273",
    "STKPRIS": "444.83",
    "STKAFREGNSATS": "0.1343",
    "BELOEB": "-16466.41",
    "VALUTA": "DKK",
    "SKAT": "0.00",
    "AFREGNBATCH": "7287"
  },
  {
    "TRANSNR": "28837",
    "TRANSTYPE": "Salg",
    "KONTO": "AUTH-0215",
    "AFTALE": "AFT-2020-099",
    "ARTNR": "978-87-3367-539-9",
    "KANAL": "Subskription",
    "PRISGRUPPE": "Lydbog",
    "VILKAR": "D",
    "BILAGSNR": "73558",
    "BILAGSDATO": "2023-03-05",
    "ANTAL": "453",
    "STKPRIS": "286.32",
    "STKAFREGNSATS": "0.2346",
    "BELOEB": "30428.31",
    "VALUTA": "DKK",
    "SKAT": "0.00",
    "AFREGNBATCH": "7287"
  },
  {
    "TRANSNR": "28838",
    "TRANSTYPE": "Retur",
    "KONTO": "AUTH-0215",
    "AFTALE": "AFT-2020-099",
    "ARTNR": "978-87-9586-905-7",
    "KANAL": "Subskription",
    "PRISGRUPPE": "Klassiker",
    "VILKAR": "D",
    "BILAGSNR": "87024",
    "BILAGSDATO": "2023-04-16",
    "ANTAL": "-1794",
    "STKPRIS": "475.23",
    "STKAFREGNSATS": "0.0807",
    "BELOEB": "-68801.80",
    "VALUTA": "DKK",
    "SKAT": "0.00",
    "AFREGNBATCH": "7287"
  },
  {
    "TRANSNR": "28839",
    "TRANSTYPE": "Salg",
    "KONTO": "AUTH-0215",
    "AFTALE": "AFT-2020-099",
    "ARTNR": "978-87-3133-079-5",
    "KANAL": "Lydbog",
    "PRISGRUPPE": "Indbundet",
    "VILKAR": "D",
    "BILAGSNR": "74806",
    "BILAGSDATO": "2023-03-16",
    "ANTAL": "1291",
    "STKPRIS": "401.39",
    "STKAFREGNSATS": "0.1513",
    "BELOEB": "78402.83",
    "VALUTA": "DKK",
    "SKAT": "0.00",
    "AFREGNBATCH": "7287"
  },
  {
    "TRANSNR": "28840",
    "TRANSTYPE": "Salg",
    "KONTO": "AUTH-0215",
    "AFTALE": "AFT-2020-099",
    "ARTNR": "978-87-4762-534-2",
    "KANAL": "Eksport",
    "PRISGRUPPE": "Indbundet",
    "VILKAR": "B",
    "BILAGSNR": "94013",
    "BILAGSDATO": "2023-04-19",
    "ANTAL": "43",
    "STKPRIS": "60.77",
    "STKAFREGNSATS": "0.0691",
    "BELOEB": "180.57",
    "VALUTA": "DKK",
    "SKAT": "0.00",
    "AFREGNBATCH": "7287"
  },
  {
    "TRANSNR": "28841",
    "TRANSTYPE": "Salg",
    "KONTO": "AUTH-0215",
    "AFTALE": "AFT-2020-099",
    "ARTNR": "978-87-9541-581-0",
    "KANAL": "Lydbog",
    "PRISGRUPPE": "Klassiker",
    "VILKAR": "C",
    "BILAGSNR": "87168",
    "BILAGSDATO": "2023-03-06",
    "ANTAL": "1410",
    "STKPRIS": "231.63",
    "STKAFREGNSATS": "0.1324",
    "BELOEB": "43309.70",
    "VALUTA": "NOK",
    "SKAT": "0.00",
    "AFREGNBATCH": "7287"
  },
  {
    "TRANSNR": "28842",
    "TRANSTYPE": "Salg",
    "KONTO": "AUTH-0215",
    "AFTALE": "AFT-2020-099",
    "ARTNR": "978-87-0010-763-2",
    "KANAL": "Lydbog",
    "PRISGRUPPE": "Digital",
    "VILKAR": "B",
    "BILAGSNR": "53518",
    "BILAGSDATO": "2023-03-17",
    "ANTAL": "416",
    "STKPRIS": "105.45",
    "STKAFREGNSATS": "0.0604",
    "BELOEB": "2649.58",
    "VALUTA": "DKK",
    "SKAT": "0.00",
    "AFREGNBATCH": "7287"
  },
  {
    "TRANSNR": "28843",
    "TRANSTYPE": "Retur",
    "KONTO": "AUTH-0215",
    "AFTALE": "AFT-2020-099",
    "ARTNR": "978-87-6238-562-7",
    "KANAL": "Bibliotek",
    "PRISGRUPPE": "Standard",
    "VILKAR": "C",
    "BILAGSNR": "66088",
    "BILAGSDATO": "2023-03-07",
    "ANTAL": "-1989",
    "STKPRIS": "154.97",
    "STKAFREGNSATS": "0.1872",
    "BELOEB": "-57981.69",
    "VALUTA": "DKK",
    "SKAT": "0.00",
    "AFREGNBATCH": "7287"
  },
  {
    "TRANSNR": "28844",
    "TRANSTYPE": "Salg",
    "KONTO": "AUTH-0215",
    "AFTALE": "AFT-2020-099",
    "ARTNR": "978-87-2922-279-8",
    "KANAL": "Lydbog",
    "PRISGRUPPE": "Indbundet",
    "VILKAR": "D",
    "BILAGSNR": "54341",
    "BILAGSDATO": "2023-04-11",
    "ANTAL": "1400",
    "STKPRIS": "460.28",
    "STKAFREGNSATS": "0.1765",
    "BELOEB": "113903.56",
    "VALUTA": "DKK",
    "SKAT": "0.00",
    "AFREGNBATCH": "7287"
  },
  {
    "TRANSNR": "28845",
    "TRANSTYPE": "Salg",
    "KONTO": "AUTH-0215",
    "AFTALE": "AFT-2020-099",
    "ARTNR": "978-87-4173-089-9",
    "KANAL": "Lydbog",
    "PRISGRUPPE": "Indbundet",
    "VILKAR": "B",
    "BILAGSNR": "92659",
    "BILAGSDATO": "2023-04-03",
    "ANTAL": "1899",
    "STKPRIS": "131.52",
    "STKAFREGNSATS": "0.0654",
    "BELOEB": "16334.07",
    "VALUTA": "DKK",
    "SKAT": "0.00",
    "AFREGNBATCH": "7287"
  },
  {
    "TRANSNR": "28846",
    "TRANSTYPE": "GarGlobal",
    "KONTO": "AUTH-0215",
    "AFTALE": "AFT-2020-099",
    "ARTNR": "978-87-0956-560-0",
    "KANAL": "Online",
    "PRISGRUPPE": "Digital",
    "VILKAR": "D",
    "BILAGSNR": "71058",
    "BILAGSDATO": "2023-03-28",
    "ANTAL": "270",
    "STKPRIS": "461.22",
    "STKAFREGNSATS": "0.1382",
    "BELOEB": "17209.96",
    "VALUTA": "DKK",
    "SKAT": "0.00",
    "AFREGNBATCH": "7287"
  },
  {
    "TRANSNR": "28847",
    "TRANSTYPE": "Royalty",
    "KONTO": "AUTH-0215",
    "AFTALE": "AFT-2020-099",
    "ARTNR": "978-87-4981-916-9",
    "KANAL": "Bibliotek",
    "PRISGRUPPE": "Special",
    "VILKAR": "C",
    "BILAGSNR": "55544",
    "BILAGSDATO": "2023-03-04",
    "ANTAL": "667",
    "STKPRIS": "497.19",
    "STKAFREGNSATS": "0.0809",
    "BELOEB": "26828.52",
    "VALUTA": "DKK",
    "SKAT": "0.00",
    "AFREGNBATCH": "7287"
  },
  {
    "TRANSNR": "28848",
    "TRANSTYPE": "Salg",
    "KONTO": "AUTH-0215",
    "AFTALE": "AFT-2020-099",
    "ARTNR": "978-87-0757-630-1",
    "KANAL": "Boghandel",
    "PRISGRUPPE": "Lydbog",
    "VILKAR": "A",
    "BILAGSNR": "84714",
    "BILAGSDATO": "2023-03-21",
    "ANTAL": "8",
    "STKPRIS": "349.04",
    "STKAFREGNSATS": "0.2135",
    "BELOEB": "596.16",
    "VALUTA": "DKK",
    "SKAT": "0.00",
    "AFREGNBATCH": "7287"
  },
  {
    "TRANSNR": "28849",
    "TRANSTYPE": "Salg",
    "KONTO": "AUTH-0215",
    "AFTALE": "AFT-2020-099",
    "ARTNR": "978-87-1196-440-8",
    "KANAL": "Subskription",
    "PRISGRUPPE": "Standard",
    "VILKAR": "A",
    "BILAGSNR": "59814",
    "BILAGSDATO": "2023-04-08",
    "ANTAL": "144",
    "STKPRIS": "531.92",
    "STKAFREGNSATS": "0.1652",
    "BELOEB": "12958.84",
    "VALUTA": "DKK",
    "SKAT": "0.00",
    "AFREGNBATCH": "7287"
  },
  {
    "TRANSNR": "28850",
    "TRANSTYPE": "Salg",
    "KONTO": "AUTH-0215",
    "AFTALE": "AFT-2020-099",
    "ARTNR": "978-87-7114-138-2",
    "KANAL": "Boghandel",
    "PRISGRUPPE": "Indbundet",
    "VILKAR": "D",
    "BILAGSNR": "87782",
    "BILAGSDATO": "2023-04-03",
    "ANTAL": "117",
    "STKPRIS": "109.56",
    "STKAFREGNSATS": "0.1956",
    "BELOEB": "2507.30",
    "VALUTA": "DKK",
    "SKAT": "0.00",
    "AFREGNBATCH": "7287"
  },
  {
    "TRANSNR": "28851",
    "TRANSTYPE": "Salg",
    "KONTO": "AUTH-0215",
    "AFTALE": "AFT-2020-099",
    "ARTNR": "978-87-6500-397-9",
    "KANAL": "Boghandel",
    "PRISGRUPPE": "Pocket",
    "VILKAR": "C",
    "BILAGSNR": "65903",
    "BILAGSDATO": "2023-04-27",
    "ANTAL": "720",
    "STKPRIS": "433.31",
    "STKAFREGNSATS": "0.1001",
    "BELOEB": "31229.52",
    "VALUTA": "DKK",
    "SKAT": "0.00",
    "AFREGNBATCH": "7287"
  },
  {
    "TRANSNR": "28852",
    "TRANSTYPE": "Royalty",
    "KONTO": "AUTH-0215",
    "AFTALE": "AFT-2020-099",
    "ARTNR": "978-87-4246-272-0",
    "KANAL": "Lydbog",
    "PRISGRUPPE": "Digital",
    "VILKAR": "C",
    "BILAGSNR": "50883",
    "BILAGSDATO": "2023-03-24",
    "ANTAL": "1966",
    "STKPRIS": "479.06",
    "STKAFREGNSATS": "0.1309",
    "BELOEB": "123172.26",
    "VALUTA": "DKK",
    "SKAT": "0.00",
    "AFREGNBATCH": "7287"
  },
  {
    "TRANSNR": "28853",
    "TRANSTYPE": "Bonus",
    "KONTO": "AUTH-0215",
    "AFTALE": "AFT-2020-099",
    "ARTNR": "978-87-5685-927-1",
    "KANAL": "Boghandel",
    "PRISGRUPPE": "Standard",
    "VILKAR": "C",
    "BILAGSNR": "81215",
    "BILAGSDATO": "2023-04-18",
    "ANTAL": "1260",
    "STKPRIS": "273.40",
    "STKAFREGNSATS": "0.1581",
    "BELOEB": "54462.92",
    "VALUTA": "DKK",
    "SKAT": "0.00",
    "AFREGNBATCH": "7287"
  },
  {
    "TRANSNR": "28854",
    "TRANSTYPE": "Salg",
    "KONTO": "AUTH-0215",
    "AFTALE": "AFT-2020-099",
    "ARTNR": "978-87-0841-994-2",
    "KANAL": "Lydbog",
    "PRISGRUPPE": "Indbundet",
    "VILKAR": "B",
    "BILAGSNR": "76675",
    "BILAGSDATO": "2023-03-12",
    "ANTAL": "618",
    "STKPRIS": "86.95",
    "STKAFREGNSATS": "0.0652",
    "BELOEB": "3503.53",
    "VALUTA": "DKK",
    "SKAT": "0.00",
    "AFREGNBATCH": "7287"
  },
  {
    "TRANSNR": "28855",
    "TRANSTYPE": "Bonus",
    "KONTO": "AUTH-0215",
    "AFTALE": "AFT-2020-099",
    "ARTNR": "978-87-0797-928-7",
    "KANAL": "Lydbog",
    "PRISGRUPPE": "Lydbog",
    "VILKAR": "C",
    "BILAGSNR": "81832",
    "BILAGSDATO": "2023-03-30",
    "ANTAL": "124",
    "STKPRIS": "509.34",
    "STKAFREGNSATS": "0.07",
    "BELOEB": "4421.07",
    "VALUTA": "DKK",
    "SKAT": "0.00",
    "AFREGNBATCH": "7287"
  },
  {
    "TRANSNR": "28856",
    "TRANSTYPE": "Salg",
    "KONTO": "AUTH-0215",
    "AFTALE": "AFT-2020-099",
    "ARTNR": "978-87-0494-945-0",
    "KANAL": "Online",
    "PRISGRUPPE": "Digital",
    "VILKAR": "A",
    "BILAGSNR": "95702",
    "BILAGSDATO": "2023-03-03",
    "ANTAL": "1313",
    "STKPRIS": "468.67",
    "STKAFREGNSATS": "0.1681",
    "BELOEB": "103338.96",
    "VALUTA": "DKK",
    "SKAT": "0.00",
    "AFREGNBATCH": "7287"
  },
  {
    "TRANSNR": "28857",
    "TRANSTYPE": "Salg",
    "KONTO": "AUTH-0215",
    "AFTALE": "AFT-2020-099",
    "ARTNR": "978-87-1012-857-3",
    "KANAL": "Boghandel",
    "PRISGRUPPE": "Lydbog",
    "VILKAR": "C",
    "BILAGSNR": "92890",
    "BILAGSDATO": "2023-03-06",
    "ANTAL": "1683",
    "STKPRIS": "77.30",
    "STKAFREGNSATS": "0.0682",
    "BELOEB": "8872.54",
    "VALUTA": "DKK",
    "SKAT": "0.00",
    "AFREGNBATCH": "7287"
  },
  {
    "TRANSNR": "28858",
    "TRANSTYPE": "Retur",
    "KONTO": "AUTH-0215",
    "AFTALE": "AFT-2020-099",
    "ARTNR": "978-87-2343-306-0",
    "KANAL": "E-bog",
    "PRISGRUPPE": "Standard",
    "VILKAR": "D",
    "BILAGSNR": "55722",
    "BILAGSDATO": "2023-04-02",
    "ANTAL": "-711",
    "STKPRIS": "304.29",
    "STKAFREGNSATS": "0.2288",
    "BELOEB": "-49500.92",
    "VALUTA": "DKK",
    "SKAT": "0.00",
    "AFREGNBATCH": "7287"
  },
  {
    "TRANSNR": "28859",
    "TRANSTYPE": "Salg",
    "KONTO": "AUTH-0215",
    "AFTALE": "AFT-2020-099",
    "ARTNR": "978-87-6615-658-2",
    "KANAL": "Online",
    "PRISGRUPPE": "Pocket",
    "VILKAR": "D",
    "BILAGSNR": "67900",
    "BILAGSDATO": "2023-03-25",
    "ANTAL": "934",
    "STKPRIS": "79.24",
    "STKAFREGNSATS": "0.1577",
    "BELOEB": "11671.40",
    "VALUTA": "DKK",
    "SKAT": "0.00",
    "AFREGNBATCH": "7287"
  },
  {
    "TRANSNR": "28860",
    "TRANSTYPE": "Royalty",
    "KONTO": "AUTH-0215",
    "AFTALE": "AFT-2020-099",
    "ARTNR": "978-87-3066-949-0",
    "KANAL": "Online",
    "PRISGRUPPE": "Indbundet",
    "VILKAR": "A",
    "BILAGSNR": "52053",
    "BILAGSDATO": "2023-04-20",
    "ANTAL": "413",
    "STKPRIS": "34.24",
    "STKAFREGNSATS": "0.1278",
    "BELOEB": "1807.24",
    "VALUTA": "DKK",
    "SKAT": "0.00",
    "AFREGNBATCH": "7287"
  },
  {
    "TRANSNR": "28861",
    "TRANSTYPE": "Salg",
    "KONTO": "AUTH-0215",
    "AFTALE": "AFT-2020-099",
    "ARTNR": "978-87-1317-662-5",
    "KANAL": "Online",
    "PRISGRUPPE": "Indbundet",
    "VILKAR": "B",
    "BILAGSNR": "70899",
    "BILAGSDATO": "2023-04-18",
    "ANTAL": "1279",
    "STKPRIS": "353.54",
    "STKAFREGNSATS": "0.2461",
    "BELOEB": "111728.71",
    "VALUTA": "DKK",
    "SKAT": "0.00",
    "AFREGNBATCH": "7287"
  },
  {
    "TRANSNR": "28862",
    "TRANSTYPE": "Salg",
    "KONTO": "AUTH-0215",
    "AFTALE": "AFT-2020-099",
    "ARTNR": "978-87-0655-896-4",
    "KANAL": "Bibliotek",
    "PRISGRUPPE": "Lydbog",
    "VILKAR": "A",
    "BILAGSNR": "55015",
    "BILAGSDATO": "2023-03-20",
    "ANTAL": "14",
    "STKPRIS": "466.40",
    "STKAFREGNSATS": "0.1912",
    "BELOEB": "1248.46",
    "VALUTA": "DKK",
    "SKAT": "0.00",
    "AFREGNBATCH": "7287"
  },
  {
    "TRANSNR": "28863",
    "TRANSTYPE": "Korrektion",
    "KONTO": "AUTH-0215",
    "AFTALE": "AFT-2020-099",
    "ARTNR": "978-87-8429-575-1",
    "KANAL": "Bibliotek",
    "PRISGRUPPE": "Standard",
    "VILKAR": "B",
    "BILAGSNR": "74689",
    "BILAGSDATO": "2023-03-13",
    "ANTAL": "1906",
    "STKPRIS": "84.07",
    "STKAFREGNSATS": "0.1484",
    "BELOEB": "23779.23",
    "VALUTA": "DKK",
    "SKAT": "0.00",
    "AFREGNBATCH": "7287"
  },
  {
    "TRANSNR": "28864",
    "TRANSTYPE": "Retur",
    "KONTO": "AUTH-0215",
    "AFTALE": "AFT-2020-099",
    "ARTNR": "978-87-0289-500-1",
    "KANAL": "Online",
    "PRISGRUPPE": "Indbundet",
    "VILKAR": "D",
    "BILAGSNR": "74780",
    "BILAGSDATO": "2023-04-20",
    "ANTAL": "-1471",
    "STKPRIS": "350.79",
    "STKAFREGNSATS": "0.1751",
    "BELOEB": "-90353.72",
    "VALUTA": "DKK",
    "SKAT": "0.00",
    "AFREGNBATCH": "7287"
  },
  {
    "TRANSNR": "28865",
    "TRANSTYPE": "Salg",
    "KONTO": "AUTH-0215",
    "AFTALE": "AFT-2020-099",
    "ARTNR": "978-87-0555-884-2",
    "KANAL": "Online",
    "PRISGRUPPE": "Klassiker",
    "VILKAR": "C",
    "BILAGSNR": "60881",
    "BILAGSDATO": "2023-04-24",
    "ANTAL": "1989",
    "STKPRIS": "359.34",
    "STKAFREGNSATS": "0.0866",
    "BELOEB": "61895.38",
    "VALUTA": "DKK",
    "SKAT": "0.00",
    "AFREGNBATCH": "7287"
  },
  {
    "TRANSNR": "28866",
    "TRANSTYPE": "Retur",
    "KONTO": "AUTH-0215",
    "AFTALE": "AFT-2020-099",
    "ARTNR": "978-87-6407-972-2",
    "KANAL": "Boghandel",
    "PRISGRUPPE": "Klassiker",
    "VILKAR": "A",
    "BILAGSNR": "81429",
    "BILAGSDATO": "2023-03-29",
    "ANTAL": "-997",
    "STKPRIS": "143.86",
    "STKAFREGNSATS": "0.162",
    "BELOEB": "-23235.40",
    "VALUTA": "DKK",
    "SKAT": "0.00",
    "AFREGNBATCH": "7287"
  },
  {
    "TRANSNR": "28867",
    "TRANSTYPE": "Salg",
    "KONTO": "AUTH-0215",
    "AFTALE": "AFT-2020-099",
    "ARTNR": "978-87-6600-589-7",
    "KANAL": "Boghandel",
    "PRISGRUPPE": "Klassiker",
    "VILKAR": "C",
    "BILAGSNR": "85208",
    "BILAGSDATO": "2023-03-09",
    "ANTAL": "984",
    "STKPRIS": "472.21",
    "STKAFREGNSATS": "0.1434",
    "BELOEB": "66631.48",
    "VALUTA": "DKK",
    "SKAT": "0.00",
    "AFREGNBATCH": "7287"
  }
]